besttags/__about__.py
besttags/__init__.py
besttags/__main__.py
besttags/apis.py
besttags/manager.py
besttags/util.py
besttags-1.0.1.dist-info/AUTHORS.rst
besttags-1.0.1.dist-info/LICENSE
besttags-1.0.1.dist-info/METADATA
besttags-1.0.1.dist-info/WHEEL
besttags-1.0.1.dist-info/entry_points.txt
besttags-1.0.1.dist-info/top_level.txt
besttags-1.0.1.dist-info/RECORD
