Metadata-Version: 2.1
Name: besttags
Version: 1.0.1
Summary: Get the best hashtags for your post
Home-page: https://github.com/axju/besttags
Author: Axel Juraske
Author-email: axel.juraske@short-report.de
License: MIT license
Keywords: besttags
Platform: UNKNOWN
Classifier: Intended Audience :: Developers
Classifier: License :: OSI Approved :: MIT License
Classifier: Natural Language :: English
Classifier: Programming Language :: Python :: 3
Classifier: Programming Language :: Python :: 3.4
Classifier: Programming Language :: Python :: 3.5
Classifier: Programming Language :: Python :: 3.6
Classifier: Programming Language :: Python :: 3.7
Requires-Dist: requests
Requires-Dist: bs4
